Metadata-Version: 1.1
Name: pydotexe
Version: 1.0.0
Summary: pyDotexe is a program that freeze Python programs into stand-alone application tool.
Home-page: https://github.com/betacode-project/pyDotexe
Author: betacode_
Author-email: betacode.net@gmail.com
License: MIT
Platform: UNKNOWN
Classifier: Environment :: Console
Classifier: Intended Audience :: Developers
Classifier: Operating System :: Microsoft :: Windows
Classifier: Programming Language :: Python :: 2
Classifier: Programming Language :: Python :: 2.7
Classifier: Programming Language :: Python :: 3
Classifier: Topic :: Software Development
Classifier: Topic :: Software Development :: Build Tools
Classifier: License :: OSI Approved :: MIT License
